sqlalchemy_schema_factory/__init__.py
sqlalchemy_schema_factory/auxiliary.py
sqlalchemy_schema_factory/conventions.py
sqlalchemy_schema_factory/factory.py
sqlalchemy_schema_factory-0.3.2.dist-info/METADATA
sqlalchemy_schema_factory-0.3.2.dist-info/WHEEL
sqlalchemy_schema_factory-0.3.2.dist-info/RECORD
