Metadata-Version: 2.1
Name: sqlalchemy-schema-factory
Version: 0.3.2
Summary: Collection of tools for building sqlalchemy schemas
Home-page: https://github.com/smairon/sqlalchemy-schema-factory
Author: Smairon
Author-email: man@smairon.ru
Requires-Python: >=3.11,<4.0
Classifier: Programming Language :: Python :: 3
Classifier: Programming Language :: Python :: 3.11
Classifier: Programming Language :: Python :: 3.12
Requires-Dist: sqlalchemy (>=2.0.0,<3.0.0)
Project-URL: Repository, https://github.com/smairon/sqlalchemy-schema-factory
